[
    {
        "lab_name": "MCH, Blood",
        "lab_value": "36.1 pg",
        "lab_time": "2116-05-15 01:20:00"
    },
    {
        "lab_name": "MCV, Blood",
        "lab_value": "103.0 fL",
        "lab_time": "2116-05-15 01:20:00"
    },
    {
        "lab_name": "Platelet Count, Blood",
        "lab_value": "147.0 K/uL",
        "lab_time": "2116-05-15 01:20:00"
    },
    {
        "lab_name": "PT, Blood",
        "lab_value": "15.4 sec",
        "lab_time": "2116-05-15 01:20:00"
    },
    {
        "lab_name": "RDW, Blood",
        "lab_value": "18.2 %",
        "lab_time": "2116-05-15 01:20:00"
    },
    {
        "lab_name": "Red Blood Cells, Blood",
        "lab_value": "1.98 m/uL",
        "lab_time": "2116-05-15 01:20:00"
    },
    {
        "lab_name": "Calculated Total CO2, Blood",
        "lab_value": "35.0 mEq/L",
        "lab_time": "2116-05-15 01:45:00"
    },
    {
        "lab_name": "pH, Blood",
        "lab_value": "7.53 units",
        "lab_time": "2116-05-15 01:45:00"
    },
    {
        "lab_name": "pO2, Blood",
        "lab_value": "183.0 mm Hg",
        "lab_time": "2116-05-15 01:45:00"
    },
    {
        "lab_name": "Hematocrit, Blood",
        "lab_value": "22.5 %",
        "lab_time": "2116-05-15 05:26:00"
    },
    {
        "lab_name": "Calculated Total CO2, Blood",
        "lab_value": "32.0 mEq/L",
        "lab_time": "2116-05-15 16:34:00"
    },
    {
        "lab_name": "pH, Blood",
        "lab_value": "7.51 units",
        "lab_time": "2116-05-15 16:34:00"
    },
    {
        "lab_name": "pO2, Blood",
        "lab_value": "156.0 mm Hg",
        "lab_time": "2116-05-15 16:34:00"
    },
    {
        "lab_name": "Creatinine, Blood",
        "lab_value": "4.1 mg/dL",
        "lab_time": "2116-05-16 01:24:00"
    },
    {
        "lab_name": "Digoxin, Blood",
        "lab_value": "2.6 ng/mL",
        "lab_time": "2116-05-16 01:24:00"
    },
    {
        "lab_name": "Phosphate, Blood",
        "lab_value": "4.9 mg/dL",
        "lab_time": "2116-05-16 01:24:00"
    },
    {
        "lab_name": "Urea Nitrogen, Blood",
        "lab_value": "29.0 mg/dL",
        "lab_time": "2116-05-16 01:24:00"
    },
    {
        "lab_name": "Hematocrit, Blood",
        "lab_value": "24.9 %",
        "lab_time": "2116-05-16 01:24:00"
    },
    {
        "lab_name": "Hemoglobin, Blood",
        "lab_value": "8.4 g/dL",
        "lab_time": "2116-05-16 01:24:00"
    },
    {
        "lab_name": "INR(PT), Blood",
        "lab_value": "1.2",
        "lab_time": "2116-05-16 01:24:00"
    },
    {
        "lab_name": "MCH, Blood",
        "lab_value": "35.4 pg",
        "lab_time": "2116-05-16 01:24:00"
    },
    {
        "lab_name": "MCV, Blood",
        "lab_value": "105.0 fL",
        "lab_time": "2116-05-16 01:24:00"
    },
    {
        "lab_name": "PT, Blood",
        "lab_value": "13.8 sec",
        "lab_time": "2116-05-16 01:24:00"
    },
    {
        "lab_name": "RDW, Blood",
        "lab_value": "18.2 %",
        "lab_time": "2116-05-16 01:24:00"
    },
    {
        "lab_name": "Red Blood Cells, Blood",
        "lab_value": "2.37 m/uL",
        "lab_time": "2116-05-16 01:24:00"
    },
    {
        "lab_name": "Creatinine, Blood",
        "lab_value": "3.6 mg/dL",
        "lab_time": "2116-05-17 05:50:00"
    },
    {
        "lab_name": "Phenytoin, Blood",
        "lab_value": "7.5 ug/mL",
        "lab_time": "2116-05-17 05:50:00"
    },
    {
        "lab_name": "Urea Nitrogen, Blood",
        "lab_value": "23.0 mg/dL",
        "lab_time": "2116-05-17 05:50:00"
    },
    {
        "lab_name": "Hematocrit, Blood",
        "lab_value": "27.4 %",
        "lab_time": "2116-05-17 05:50:00"
    },
    {
        "lab_name": "Hemoglobin, Blood",
        "lab_value": "9.7 g/dL",
        "lab_time": "2116-05-17 05:50:00"
    },
    {
        "lab_name": "MCH, Blood",
        "lab_value": "35.7 pg",
        "lab_time": "2116-05-17 05:50:00"
    },
    {
        "lab_name": "MCHC, Blood",
        "lab_value": "35.3 %",
        "lab_time": "2116-05-17 05:50:00"
    },
    {
        "lab_name": "MCV, Blood",
        "lab_value": "101.0 fL",
        "lab_time": "2116-05-17 05:50:00"
    },
    {
        "lab_name": "RDW, Blood",
        "lab_value": "18.9 %",
        "lab_time": "2116-05-17 05:50:00"
    },
    {
        "lab_name": "Red Blood Cells, Blood",
        "lab_value": "2.72 m/uL",
        "lab_time": "2116-05-17 05:50:00"
    },
    {
        "lab_name": "Creatinine, Blood",
        "lab_value": "4.8 mg/dL",
        "lab_time": "2116-05-18 05:45:00"
    },
    {
        "lab_name": "Glucose, Blood",
        "lab_value": "107.0 mg/dL",
        "lab_time": "2116-05-18 05:45:00"
    },
    {
        "lab_name": "Urea Nitrogen, Blood",
        "lab_value": "34.0 mg/dL",
        "lab_time": "2116-05-18 05:45:00"
    },
    {
        "lab_name": "Creatinine, Blood",
        "lab_value": "5.5 mg/dL",
        "lab_time": "2116-05-19 07:00:00"
    },
    {
        "lab_name": "Glucose, Blood",
        "lab_value": "183.0 mg/dL",
        "lab_time": "2116-05-19 07:00:00"
    },
    {
        "lab_name": "Hematocrit, Blood",
        "lab_value": "26.5 %",
        "lab_time": "2116-05-19 07:00:00"
    },
    {
        "lab_name": "Hemoglobin, Blood",
        "lab_value": "9.2 g/dL",
        "lab_time": "2116-05-19 07:00:00"
    },
    {
        "lab_name": "MCH, Blood",
        "lab_value": "34.5 pg",
        "lab_time": "2116-05-19 07:00:00"
    },
    {
        "lab_name": "MCV, Blood",
        "lab_value": "100.0 fL",
        "lab_time": "2116-05-19 07:00:00"
    },
    {
        "lab_name": "RDW, Blood",
        "lab_value": "18.4 %",
        "lab_time": "2116-05-19 07:00:00"
    },
    {
        "lab_name": "Red Blood Cells, Blood",
        "lab_value": "2.66 m/uL",
        "lab_time": "2116-05-19 07:00:00"
    },
    {
        "lab_name": "Hemoglobin, Blood",
        "lab_value": "8.2 g/dL",
        "lab_time": "2116-06-04 10:40:00"
    },
    {
        "lab_name": "Creatinine, Blood",
        "lab_value": "5.9 mg/dL",
        "lab_time": "2116-07-14 10:30:00"
    },
    {
        "lab_name": "Glucose, Blood",
        "lab_value": "148.0 mg/dL",
        "lab_time": "2116-07-14 10:30:00"
    },
    {
        "lab_name": "Urea Nitrogen, Blood",
        "lab_value": "65.0 mg/dL",
        "lab_time": "2116-07-14 10:30:00"
    },
    {
        "lab_name": "Vitamin B12, Blood",
        "lab_value": "1066.0 pg/mL",
        "lab_time": "2116-07-14 10:30:00"
    },
    {
        "lab_name": "Hematocrit, Blood",
        "lab_value": "31.9 %",
        "lab_time": "2116-07-14 10:30:00"
    },
    {
        "lab_name": "Hemoglobin, Blood",
        "lab_value": "10.4 g/dL",
        "lab_time": "2116-07-14 10:30:00"
    },
    {
        "lab_name": "MCH, Blood",
        "lab_value": "33.3 pg",
        "lab_time": "2116-07-14 10:30:00"
    },
    {
        "lab_name": "MCV, Blood",
        "lab_value": "102.0 fL",
        "lab_time": "2116-07-14 10:30:00"
    },
    {
        "lab_name": "RDW, Blood",
        "lab_value": "16.8 %",
        "lab_time": "2116-07-14 10:30:00"
    },
    {
        "lab_name": "Red Blood Cells, Blood",
        "lab_value": "3.12 m/uL",
        "lab_time": "2116-07-14 10:30:00"
    },
    {
        "lab_name": "Chloride, Whole Blood, Blood",
        "lab_value": "99.0 mEq/L",
        "lab_time": "2116-08-26 14:58:00"
    },
    {
        "lab_name": "Hemoglobin, Blood",
        "lab_value": "13.2 g/dL",
        "lab_time": "2116-08-26 14:58:00"
    },
    {
        "lab_name": "Bicarbonate, Blood",
        "lab_value": "21.0 mEq/L",
        "lab_time": "2116-08-27 05:45:00"
    },
    {
        "lab_name": "Creatinine, Blood",
        "lab_value": "6.3 mg/dL",
        "lab_time": "2116-08-27 05:45:00"
    },
    {
        "lab_name": "Phosphate, Blood",
        "lab_value": "5.7 mg/dL",
        "lab_time": "2116-08-27 05:45:00"
    },
    {
        "lab_name": "Urea Nitrogen, Blood",
        "lab_value": "73.0 mg/dL",
        "lab_time": "2116-08-27 05:45:00"
    },
    {
        "lab_name": "Hematocrit, Blood",
        "lab_value": "34.4 %",
        "lab_time": "2116-08-27 05:45:00"
    },
    {
        "lab_name": "Hemoglobin, Blood",
        "lab_value": "11.5 g/dL",
        "lab_time": "2116-08-27 05:45:00"
    },
    {
        "lab_name": "INR(PT), Blood",
        "lab_value": "1.3",
        "lab_time": "2116-08-27 05:45:00"
    },
    {
        "lab_name": "MCH, Blood",
        "lab_value": "33.0 pg",
        "lab_time": "2116-08-27 05:45:00"
    },
    {
        "lab_name": "MCV, Blood",
        "lab_value": "99.0 fL",
        "lab_time": "2116-08-27 05:45:00"
    },
    {
        "lab_name": "Platelet Count, Blood",
        "lab_value": "111.0 K/uL",
        "lab_time": "2116-08-27 05:45:00"
    },
    {
        "lab_name": "PT, Blood",
        "lab_value": "14.3 sec",
        "lab_time": "2116-08-27 05:45:00"
    },
    {
        "lab_name": "RDW, Blood",
        "lab_value": "17.3 %",
        "lab_time": "2116-08-27 05:45:00"
    },
    {
        "lab_name": "Red Blood Cells, Blood",
        "lab_value": "3.48 m/uL",
        "lab_time": "2116-08-27 05:45:00"
    },
    {
        "lab_name": "Creatinine, Blood",
        "lab_value": "6.3 mg/dL",
        "lab_time": "2116-09-02 16:48:00"
    },
    {
        "lab_name": "Glucose, Blood",
        "lab_value": "167.0 mg/dL",
        "lab_time": "2116-09-02 16:48:00"
    },
    {
        "lab_name": "Urea Nitrogen, Blood",
        "lab_value": "62.0 mg/dL",
        "lab_time": "2116-09-02 16:48:00"
    },
    {
        "lab_name": "Hematocrit, Blood",
        "lab_value": "35.3 %",
        "lab_time": "2116-09-02 16:48:00"
    },
    {
        "lab_name": "Hemoglobin, Blood",
        "lab_value": "11.8 g/dL",
        "lab_time": "2116-09-02 16:48:00"
    },
    {
        "lab_name": "INR(PT), Blood",
        "lab_value": "1.3",
        "lab_time": "2116-09-02 16:48:00"
    },
    {
        "lab_name": "MCH, Blood",
        "lab_value": "33.3 pg",
        "lab_time": "2116-09-02 16:48:00"
    },
    {
        "lab_name": "MCV, Blood",
        "lab_value": "100.0 fL",
        "lab_time": "2116-09-02 16:48:00"
    },
    {
        "lab_name": "Platelet Count, Blood",
        "lab_value": "118.0 K/uL",
        "lab_time": "2116-09-02 16:48:00"
    },
    {
        "lab_name": "PT, Blood",
        "lab_value": "14.2 sec",
        "lab_time": "2116-09-02 16:48:00"
    },
    {
        "lab_name": "RDW, Blood",
        "lab_value": "17.4 %",
        "lab_time": "2116-09-02 16:48:00"
    },
    {
        "lab_name": "Red Blood Cells, Blood",
        "lab_value": "3.53 m/uL",
        "lab_time": "2116-09-02 16:48:00"
    },
    {
        "lab_name": "Creatinine, Blood",
        "lab_value": "5.0 mg/dL",
        "lab_time": "2116-09-04 07:15:00"
    },
    {
        "lab_name": "Glucose, Blood",
        "lab_value": "132.0 mg/dL",
        "lab_time": "2116-09-04 07:15:00"
    },
    {
        "lab_name": "Urea Nitrogen, Blood",
        "lab_value": "45.0 mg/dL",
        "lab_time": "2116-09-04 07:15:00"
    },
    {
        "lab_name": "Hematocrit, Blood",
        "lab_value": "33.2 %",
        "lab_time": "2116-09-04 07:15:00"
    },
    {
        "lab_name": "Hemoglobin, Blood",
        "lab_value": "11.1 g/dL",
        "lab_time": "2116-09-04 07:15:00"
    },
    {
        "lab_name": "MCH, Blood",
        "lab_value": "33.9 pg",
        "lab_time": "2116-09-04 07:15:00"
    },
    {
        "lab_name": "MCV, Blood",
        "lab_value": "102.0 fL",
        "lab_time": "2116-09-04 07:15:00"
    },
    {
        "lab_name": "Platelet Count, Blood",
        "lab_value": "136.0 K/uL",
        "lab_time": "2116-09-04 07:15:00"
    },
    {
        "lab_name": "RDW, Blood",
        "lab_value": "17.3 %",
        "lab_time": "2116-09-04 07:15:00"
    },
    {
        "lab_name": "Red Blood Cells, Blood",
        "lab_value": "3.26 m/uL",
        "lab_time": "2116-09-04 07:15:00"
    },
    {
        "lab_name": "Creatinine, Blood",
        "lab_value": "5.1 mg/dL",
        "lab_time": "2116-09-08 17:40:00"
    },
    {
        "lab_name": "Glucose, Blood",
        "lab_value": "132.0 mg/dL",
        "lab_time": "2116-09-08 17:40:00"
    },
    {
        "lab_name": "Urea Nitrogen, Blood",
        "lab_value": "36.0 mg/dL",
        "lab_time": "2116-09-08 17:40:00"
    },
    {
        "lab_name": "Eosinophils, Blood",
        "lab_value": "4.2 %",
        "lab_time": "2116-09-08 17:40:00"
    },
    {
        "lab_name": "Hematocrit, Blood",
        "lab_value": "30.7 %",
        "lab_time": "2116-09-08 17:40:00"
    },
    {
        "lab_name": "Hemoglobin, Blood",
        "lab_value": "10.2 g/dL",
        "lab_time": "2116-09-08 17:40:00"
    },
    {
        "lab_name": "MCH, Blood",
        "lab_value": "34.0 pg",
        "lab_time": "2116-09-08 17:40:00"
    },
    {
        "lab_name": "MCV, Blood",
        "lab_value": "102.0 fL",
        "lab_time": "2116-09-08 17:40:00"
    },
    {
        "lab_name": "Platelet Count, Blood",
        "lab_value": "148.0 K/uL",
        "lab_time": "2116-09-08 17:40:00"
    },
    {
        "lab_name": "RDW, Blood",
        "lab_value": "16.9 %",
        "lab_time": "2116-09-08 17:40:00"
    },
    {
        "lab_name": "Red Blood Cells, Blood",
        "lab_value": "3.01 m/uL",
        "lab_time": "2116-09-08 17:40:00"
    },
    {
        "lab_name": "Creatinine, Blood",
        "lab_value": "5.8 mg/dL",
        "lab_time": "2116-09-09 05:30:00"
    },
    {
        "lab_name": "Phosphate, Blood",
        "lab_value": "4.8 mg/dL",
        "lab_time": "2116-09-09 05:30:00"
    },
    {
        "lab_name": "Urea Nitrogen, Blood",
        "lab_value": "45.0 mg/dL",
        "lab_time": "2116-09-09 05:30:00"
    },
    {
        "lab_name": "Hematocrit, Blood",
        "lab_value": "27.7 %",
        "lab_time": "2116-09-09 05:30:00"
    },
    {
        "lab_name": "Hemoglobin, Blood",
        "lab_value": "9.3 g/dL",
        "lab_time": "2116-09-09 05:30:00"
    },
    {
        "lab_name": "MCH, Blood",
        "lab_value": "34.2 pg",
        "lab_time": "2116-09-09 05:30:00"
    },
    {
        "lab_name": "MCV, Blood",
        "lab_value": "102.0 fL",
        "lab_time": "2116-09-09 05:30:00"
    },
    {
        "lab_name": "Platelet Count, Blood",
        "lab_value": "146.0 K/uL",
        "lab_time": "2116-09-09 05:30:00"
    },
    {
        "lab_name": "PT, Blood",
        "lab_value": "13.2 sec",
        "lab_time": "2116-09-09 05:30:00"
    },
    {
        "lab_name": "RDW, Blood",
        "lab_value": "17.1 %",
        "lab_time": "2116-09-09 05:30:00"
    },
    {
        "lab_name": "Red Blood Cells, Blood",
        "lab_value": "2.71 m/uL",
        "lab_time": "2116-09-09 05:30:00"
    },
    {
        "lab_name": "Hematocrit, Blood",
        "lab_value": "29.5 %",
        "lab_time": "2116-09-10 17:00:00"
    },
    {
        "lab_name": "Hemoglobin, Blood",
        "lab_value": "9.3 g/dL",
        "lab_time": "2116-09-10 17:00:00"
    },
    {
        "lab_name": "INR(PT), Blood",
        "lab_value": "1.2",
        "lab_time": "2116-09-10 17:00:00"
    },
    {
        "lab_name": "MCH, Blood",
        "lab_value": "32.8 pg",
        "lab_time": "2116-09-10 17:00:00"
    },
    {
        "lab_name": "MCV, Blood",
        "lab_value": "104.0 fL",
        "lab_time": "2116-09-10 17:00:00"
    },
    {
        "lab_name": "Platelet Count, Blood",
        "lab_value": "129.0 K/uL",
        "lab_time": "2116-09-10 17:00:00"
    },
    {
        "lab_name": "PT, Blood",
        "lab_value": "13.5 sec",
        "lab_time": "2116-09-10 17:00:00"
    },
    {
        "lab_name": "RDW, Blood",
        "lab_value": "17.4 %",
        "lab_time": "2116-09-10 17:00:00"
    },
    {
        "lab_name": "Red Blood Cells, Blood",
        "lab_value": "2.85 m/uL",
        "lab_time": "2116-09-10 17:00:00"
    },
    {
        "lab_name": "Creatinine, Blood",
        "lab_value": "5.5 mg/dL",
        "lab_time": "2116-09-11 06:50:00"
    },
    {
        "lab_name": "Glucose, Blood",
        "lab_value": "131.0 mg/dL",
        "lab_time": "2116-09-11 06:50:00"
    },
    {
        "lab_name": "Phosphate, Blood",
        "lab_value": "4.7 mg/dL",
        "lab_time": "2116-09-11 06:50:00"
    },
    {
        "lab_name": "Hematocrit, Blood",
        "lab_value": "27.5 %",
        "lab_time": "2116-04-28 15:46:00"
    },
    {
        "lab_name": "Hemoglobin, Blood",
        "lab_value": "10.0 g/dL",
        "lab_time": "2116-04-28 15:46:00"
    },
    {
        "lab_name": "MCH, Blood",
        "lab_value": "37.9 pg",
        "lab_time": "2116-04-28 15:46:00"
    },
    {
        "lab_name": "MCHC, Blood",
        "lab_value": "36.4 %",
        "lab_time": "2116-04-28 15:46:00"
    },
    {
        "lab_name": "MCV, Blood",
        "lab_value": "104.0 fL",
        "lab_time": "2116-04-28 15:46:00"
    },
    {
        "lab_name": "RDW, Blood",
        "lab_value": "19.3 %",
        "lab_time": "2116-04-28 15:46:00"
    },
    {
        "lab_name": "Red Blood Cells, Blood",
        "lab_value": "2.64 m/uL",
        "lab_time": "2116-04-28 15:46:00"
    },
    {
        "lab_name": "Hematocrit, Blood",
        "lab_value": "28.1 %",
        "lab_time": "2116-05-05 15:10:00"
    },
    {
        "lab_name": "Hemoglobin, Blood",
        "lab_value": "9.7 g/dL",
        "lab_time": "2116-05-05 15:10:00"
    },
    {
        "lab_name": "MCH, Blood",
        "lab_value": "36.7 pg",
        "lab_time": "2116-05-05 15:10:00"
    },
    {
        "lab_name": "MCV, Blood",
        "lab_value": "106.0 fL",
        "lab_time": "2116-05-05 15:10:00"
    },
    {
        "lab_name": "RDW, Blood",
        "lab_value": "19.1 %",
        "lab_time": "2116-05-05 15:10:00"
    },
    {
        "lab_name": "Red Blood Cells, Blood",
        "lab_value": "2.65 m/uL",
        "lab_time": "2116-05-05 15:10:00"
    },
    {
        "lab_name": "INR(PT), Blood",
        "lab_value": "2.7",
        "lab_time": "2116-05-07 10:55:00"
    },
    {
        "lab_name": "PT, Blood",
        "lab_value": "26.2 sec",
        "lab_time": "2116-05-07 10:55:00"
    },
    {
        "lab_name": "Bicarbonate, Blood",
        "lab_value": "33.0 mEq/L",
        "lab_time": "2116-05-14 11:20:00"
    },
    {
        "lab_name": "Creatinine, Blood",
        "lab_value": "4.9 mg/dL",
        "lab_time": "2116-05-14 11:20:00"
    },
    {
        "lab_name": "Glucose, Blood",
        "lab_value": "136.0 mg/dL",
        "lab_time": "2116-05-14 11:20:00"
    },
    {
        "lab_name": "Urea Nitrogen, Blood",
        "lab_value": "41.0 mg/dL",
        "lab_time": "2116-05-14 11:20:00"
    },
    {
        "lab_name": "INR(PT), Blood",
        "lab_value": "1.6",
        "lab_time": "2116-05-14 11:20:00"
    },
    {
        "lab_name": "PT, Blood",
        "lab_value": "17.4 sec",
        "lab_time": "2116-05-14 11:20:00"
    },
    {
        "lab_name": "Hemoglobin, Blood",
        "lab_value": "9.5 g/dL",
        "lab_time": "2116-05-14 11:27:00"
    },
    {
        "lab_name": "Creatinine, Blood",
        "lab_value": "5.1 mg/dL",
        "lab_time": "2116-05-14 20:54:00"
    },
    {
        "lab_name": "Digoxin, Blood",
        "lab_value": "2.3 ng/mL",
        "lab_time": "2116-05-14 20:54:00"
    },
    {
        "lab_name": "Glucose, Blood",
        "lab_value": "152.0 mg/dL",
        "lab_time": "2116-05-14 20:54:00"
    },
    {
        "lab_name": "Urea Nitrogen, Blood",
        "lab_value": "44.0 mg/dL",
        "lab_time": "2116-05-14 20:54:00"
    },
    {
        "lab_name": "Hematocrit, Blood",
        "lab_value": "23.4 %",
        "lab_time": "2116-05-14 20:54:00"
    },
    {
        "lab_name": "Hemoglobin, Blood",
        "lab_value": "8.1 g/dL",
        "lab_time": "2116-05-14 20:54:00"
    },
    {
        "lab_name": "INR(PT), Blood",
        "lab_value": "1.6",
        "lab_time": "2116-05-14 20:54:00"
    },
    {
        "lab_name": "MCH, Blood",
        "lab_value": "36.1 pg",
        "lab_time": "2116-05-14 20:54:00"
    },
    {
        "lab_name": "MCV, Blood",
        "lab_value": "105.0 fL",
        "lab_time": "2116-05-14 20:54:00"
    },
    {
        "lab_name": "PT, Blood",
        "lab_value": "16.8 sec",
        "lab_time": "2116-05-14 20:54:00"
    },
    {
        "lab_name": "RDW, Blood",
        "lab_value": "18.2 %",
        "lab_time": "2116-05-14 20:54:00"
    },
    {
        "lab_name": "Red Blood Cells, Blood",
        "lab_value": "2.23 m/uL",
        "lab_time": "2116-05-14 20:54:00"
    },
    {
        "lab_name": "Calculated Total CO2, Blood",
        "lab_value": "32.0 mEq/L",
        "lab_time": "2116-05-14 21:08:00"
    },
    {
        "lab_name": "pH, Blood",
        "lab_value": "7.47 units",
        "lab_time": "2116-05-14 21:08:00"
    },
    {
        "lab_name": "pO2, Blood",
        "lab_value": "436.0 mm Hg",
        "lab_time": "2116-05-14 21:08:00"
    },
    {
        "lab_name": "INR(PT), Blood",
        "lab_value": "1.5",
        "lab_time": "2116-05-14 23:35:00"
    },
    {
        "lab_name": "PT, Blood",
        "lab_value": "16.0 sec",
        "lab_time": "2116-05-14 23:35:00"
    },
    {
        "lab_name": "Creatinine, Blood",
        "lab_value": "5.1 mg/dL",
        "lab_time": "2116-05-15 01:20:00"
    },
    {
        "lab_name": "Glucose, Blood",
        "lab_value": "108.0 mg/dL",
        "lab_time": "2116-05-15 01:20:00"
    },
    {
        "lab_name": "Phosphate, Blood",
        "lab_value": "4.7 mg/dL",
        "lab_time": "2116-05-15 01:20:00"
    },
    {
        "lab_name": "Urea Nitrogen, Blood",
        "lab_value": "45.0 mg/dL",
        "lab_time": "2116-05-15 01:20:00"
    },
    {
        "lab_name": "Hematocrit, Blood",
        "lab_value": "20.4 %",
        "lab_time": "2116-05-15 01:20:00"
    },
    {
        "lab_name": "Hemoglobin, Blood",
        "lab_value": "7.1 g/dL",
        "lab_time": "2116-05-15 01:20:00"
    },
    {
        "lab_name": "INR(PT), Blood",
        "lab_value": "1.4",
        "lab_time": "2116-05-15 01:20:00"
    },
    {
        "lab_name": "Urea Nitrogen, Blood",
        "lab_value": "42.0 mg/dL",
        "lab_time": "2116-09-11 06:50:00"
    },
    {
        "lab_name": "Hematocrit, Blood",
        "lab_value": "28.6 %",
        "lab_time": "2116-09-11 06:50:00"
    },
    {
        "lab_name": "Hemoglobin, Blood",
        "lab_value": "9.3 g/dL",
        "lab_time": "2116-09-11 06:50:00"
    },
    {
        "lab_name": "MCH, Blood",
        "lab_value": "33.3 pg",
        "lab_time": "2116-09-11 06:50:00"
    },
    {
        "lab_name": "MCV, Blood",
        "lab_value": "103.0 fL",
        "lab_time": "2116-09-11 06:50:00"
    },
    {
        "lab_name": "Platelet Count, Blood",
        "lab_value": "143.0 K/uL",
        "lab_time": "2116-09-11 06:50:00"
    },
    {
        "lab_name": "RDW, Blood",
        "lab_value": "17.3 %",
        "lab_time": "2116-09-11 06:50:00"
    },
    {
        "lab_name": "Red Blood Cells, Blood",
        "lab_value": "2.78 m/uL",
        "lab_time": "2116-09-11 06:50:00"
    },
    {
        "lab_name": "Digoxin, Blood",
        "lab_value": "0.3 ng/mL",
        "lab_time": "2117-01-08 11:45:00"
    },
    {
        "lab_name": "Anion Gap, Blood",
        "lab_value": "21.0 mEq/L",
        "lab_time": "2117-02-01 10:30:00"
    },
    {
        "lab_name": "Creatinine, Blood",
        "lab_value": "7.4 mg/dL",
        "lab_time": "2117-02-01 10:30:00"
    },
    {
        "lab_name": "Glucose, Blood",
        "lab_value": "160.0 mg/dL",
        "lab_time": "2117-02-01 10:30:00"
    },
    {
        "lab_name": "Troponin T, Blood",
        "lab_value": "0.37 ng/mL",
        "lab_time": "2117-02-01 10:30:00"
    },
    {
        "lab_name": "Urea Nitrogen, Blood",
        "lab_value": "53.0 mg/dL",
        "lab_time": "2117-02-01 10:30:00"
    },
    {
        "lab_name": "Hematocrit, Blood",
        "lab_value": "36.6 %",
        "lab_time": "2117-02-01 10:30:00"
    },
    {
        "lab_name": "Hemoglobin, Blood",
        "lab_value": "11.8 g/dL",
        "lab_time": "2117-02-01 10:30:00"
    },
    {
        "lab_name": "MCH, Blood",
        "lab_value": "33.7 pg",
        "lab_time": "2117-02-01 10:30:00"
    },
    {
        "lab_name": "MCV, Blood",
        "lab_value": "105.0 fL",
        "lab_time": "2117-02-01 10:30:00"
    },
    {
        "lab_name": "Neutrophils, Blood",
        "lab_value": "75.0 %",
        "lab_time": "2117-02-01 10:30:00"
    },
    {
        "lab_name": "Platelet Count, Blood",
        "lab_value": "126.0 K/uL",
        "lab_time": "2117-02-01 10:30:00"
    },
    {
        "lab_name": "RDW, Blood",
        "lab_value": "18.0 %",
        "lab_time": "2117-02-01 10:30:00"
    },
    {
        "lab_name": "Red Blood Cells, Blood",
        "lab_value": "3.5 m/uL",
        "lab_time": "2117-02-01 10:30:00"
    },
    {
        "lab_name": "Troponin T, Blood",
        "lab_value": "0.38 ng/mL",
        "lab_time": "2117-02-01 18:10:00"
    },
    {
        "lab_name": "Creatinine, Blood",
        "lab_value": "7.9 mg/dL",
        "lab_time": "2117-02-02 04:00:00"
    },
    {
        "lab_name": "Urea Nitrogen, Blood",
        "lab_value": "60.0 mg/dL",
        "lab_time": "2117-02-02 04:00:00"
    },
    {
        "lab_name": "Hematocrit, Blood",
        "lab_value": "36.3 %",
        "lab_time": "2117-02-02 04:00:00"
    },
    {
        "lab_name": "Hemoglobin, Blood",
        "lab_value": "11.5 g/dL",
        "lab_time": "2117-02-02 04:00:00"
    },
    {
        "lab_name": "INR(PT), Blood",
        "lab_value": "1.4",
        "lab_time": "2117-02-02 04:00:00"
    },
    {
        "lab_name": "MCH, Blood",
        "lab_value": "33.1 pg",
        "lab_time": "2117-02-02 04:00:00"
    },
    {
        "lab_name": "MCV, Blood",
        "lab_value": "104.0 fL",
        "lab_time": "2117-02-02 04:00:00"
    },
    {
        "lab_name": "Platelet Count, Blood",
        "lab_value": "117.0 K/uL",
        "lab_time": "2117-02-02 04:00:00"
    },
    {
        "lab_name": "PT, Blood",
        "lab_value": "16.0 sec",
        "lab_time": "2117-02-02 04:00:00"
    },
    {
        "lab_name": "RDW, Blood",
        "lab_value": "18.1 %",
        "lab_time": "2117-02-02 04:00:00"
    },
    {
        "lab_name": "Red Blood Cells, Blood",
        "lab_value": "3.49 m/uL",
        "lab_time": "2117-02-02 04:00:00"
    },
    {
        "lab_name": "Hyaline Casts, Urine",
        "lab_value": "7.0 #/lpf",
        "lab_time": "2117-02-02 23:02:00"
    },
    {
        "lab_name": "Creatinine, Blood",
        "lab_value": "5.5 mg/dL",
        "lab_time": "2117-02-03 04:50:00"
    },
    {
        "lab_name": "Urea Nitrogen, Blood",
        "lab_value": "33.0 mg/dL",
        "lab_time": "2117-02-03 04:50:00"
    },
    {
        "lab_name": "Hematocrit, Blood",
        "lab_value": "36.2 %",
        "lab_time": "2117-02-03 04:50:00"
    },
    {
        "lab_name": "Hemoglobin, Blood",
        "lab_value": "11.3 g/dL",
        "lab_time": "2117-02-03 04:50:00"
    },
    {
        "lab_name": "MCH, Blood",
        "lab_value": "32.8 pg",
        "lab_time": "2117-02-03 04:50:00"
    },
    {
        "lab_name": "MCV, Blood",
        "lab_value": "105.0 fL",
        "lab_time": "2117-02-03 04:50:00"
    },
    {
        "lab_name": "Platelet Count, Blood",
        "lab_value": "135.0 K/uL",
        "lab_time": "2117-02-03 04:50:00"
    },
    {
        "lab_name": "RDW, Blood",
        "lab_value": "17.3 %",
        "lab_time": "2117-02-03 04:50:00"
    },
    {
        "lab_name": "Red Blood Cells, Blood",
        "lab_value": "3.44 m/uL",
        "lab_time": "2117-02-03 04:50:00"
    },
    {
        "lab_name": "Amylase, Blood",
        "lab_value": "120.0 IU/L",
        "lab_time": "2117-02-11 19:58:00"
    },
    {
        "lab_name": "Creatinine, Blood",
        "lab_value": "4.8 mg/dL",
        "lab_time": "2117-02-11 19:58:00"
    },
    {
        "lab_name": "Troponin T, Blood",
        "lab_value": "0.28 ng/mL",
        "lab_time": "2117-02-11 19:58:00"
    },
    {
        "lab_name": "Urea Nitrogen, Blood",
        "lab_value": "27.0 mg/dL",
        "lab_time": "2117-02-11 19:58:00"
    },
    {
        "lab_name": "Hematocrit, Blood",
        "lab_value": "33.4 %",
        "lab_time": "2117-02-11 19:58:00"
    },
    {
        "lab_name": "Hemoglobin, Blood",
        "lab_value": "10.8 g/dL",
        "lab_time": "2117-02-11 19:58:00"
    },
    {
        "lab_name": "MCH, Blood",
        "lab_value": "33.7 pg",
        "lab_time": "2117-02-11 19:58:00"
    },
    {
        "lab_name": "MCV, Blood",
        "lab_value": "104.0 fL",
        "lab_time": "2117-02-11 19:58:00"
    },
    {
        "lab_name": "Neutrophils, Blood",
        "lab_value": "70.6 %",
        "lab_time": "2117-02-11 19:58:00"
    },
    {
        "lab_name": "Platelet Count, Blood",
        "lab_value": "126.0 K/uL",
        "lab_time": "2117-02-11 19:58:00"
    },
    {
        "lab_name": "RDW, Blood",
        "lab_value": "17.5 %",
        "lab_time": "2117-02-11 19:58:00"
    },
    {
        "lab_name": "Red Blood Cells, Blood",
        "lab_value": "3.22 m/uL",
        "lab_time": "2117-02-11 19:58:00"
    },
    {
        "lab_name": "INR(PT), Blood",
        "lab_value": "1.5",
        "lab_time": "2117-02-11 20:06:00"
    },
    {
        "lab_name": "PT, Blood",
        "lab_value": "16.4 sec",
        "lab_time": "2117-02-11 20:06:00"
    },
    {
        "lab_name": "Calcium, Total, Blood",
        "lab_value": "10.4 mg/dL",
        "lab_time": "2117-02-12 06:15:00"
    },
    {
        "lab_name": "Creatinine, Blood",
        "lab_value": "5.5 mg/dL",
        "lab_time": "2117-02-12 06:15:00"
    },
    {
        "lab_name": "Digoxin, Blood",
        "lab_value": "0.3 ng/mL",
        "lab_time": "2117-02-12 06:15:00"
    },
    {
        "lab_name": "Troponin T, Blood",
        "lab_value": "0.36 ng/mL",
        "lab_time": "2117-02-12 06:15:00"
    },
    {
        "lab_name": "Urea Nitrogen, Blood",
        "lab_value": "30.0 mg/dL",
        "lab_time": "2117-02-12 06:15:00"
    },
    {
        "lab_name": "Hematocrit, Blood",
        "lab_value": "37.2 %",
        "lab_time": "2117-02-12 06:15:00"
    },
    {
        "lab_name": "Hemoglobin, Blood",
        "lab_value": "11.5 g/dL",
        "lab_time": "2117-02-12 06:15:00"
    },
    {
        "lab_name": "INR(PT), Blood",
        "lab_value": "1.4",
        "lab_time": "2117-02-12 06:15:00"
    },
    {
        "lab_name": "MCH, Blood",
        "lab_value": "32.5 pg",
        "lab_time": "2117-02-12 06:15:00"
    },
    {
        "lab_name": "MCHC, Blood",
        "lab_value": "30.9 %",
        "lab_time": "2117-02-12 06:15:00"
    },
    {
        "lab_name": "MCV, Blood",
        "lab_value": "105.0 fL",
        "lab_time": "2117-02-12 06:15:00"
    },
    {
        "lab_name": "Platelet Count, Blood",
        "lab_value": "138.0 K/uL",
        "lab_time": "2117-02-12 06:15:00"
    },
    {
        "lab_name": "PT, Blood",
        "lab_value": "16.0 sec",
        "lab_time": "2117-02-12 06:15:00"
    },
    {
        "lab_name": "RDW, Blood",
        "lab_value": "18.4 %",
        "lab_time": "2117-02-12 06:15:00"
    },
    {
        "lab_name": "Red Blood Cells, Blood",
        "lab_value": "3.53 m/uL",
        "lab_time": "2117-02-12 06:15:00"
    },
    {
        "lab_name": "Creatinine, Blood",
        "lab_value": "4.6 mg/dL",
        "lab_time": "2117-02-13 12:05:00"
    },
    {
        "lab_name": "Troponin T, Blood",
        "lab_value": "0.35 ng/mL",
        "lab_time": "2117-02-13 12:05:00"
    },
    {
        "lab_name": "Urea Nitrogen, Blood",
        "lab_value": "23.0 mg/dL",
        "lab_time": "2117-02-13 12:05:00"
    },
    {
        "lab_name": "Hematocrit, Blood",
        "lab_value": "37.0 %",
        "lab_time": "2117-02-13 12:05:00"
    },
    {
        "lab_name": "Hemoglobin, Blood",
        "lab_value": "11.8 g/dL",
        "lab_time": "2117-02-13 12:05:00"
    },
    {
        "lab_name": "MCH, Blood",
        "lab_value": "34.0 pg",
        "lab_time": "2117-02-13 12:05:00"
    },
    {
        "lab_name": "MCV, Blood",
        "lab_value": "107.0 fL",
        "lab_time": "2117-02-13 12:05:00"
    },
    {
        "lab_name": "Platelet Count, Blood",
        "lab_value": "146.0 K/uL",
        "lab_time": "2117-02-13 12:05:00"
    },
    {
        "lab_name": "RDW, Blood",
        "lab_value": "17.6 %",
        "lab_time": "2117-02-13 12:05:00"
    },
    {
        "lab_name": "Red Blood Cells, Blood",
        "lab_value": "3.47 m/uL",
        "lab_time": "2117-02-13 12:05:00"
    },
    {
        "lab_name": "WBC, Urine",
        "lab_value": "nan #/hpf",
        "lab_time": "2117-02-13 16:03:00"
    },
    {
        "lab_name": "Troponin T, Blood",
        "lab_value": "0.32 ng/mL",
        "lab_time": "2117-02-13 17:45:00"
    },
    {
        "lab_name": "pCO2, Blood",
        "lab_value": "30.0 mm Hg",
        "lab_time": "2117-02-13 18:10:00"
    },
    {
        "lab_name": "pH, Blood",
        "lab_value": "7.53 units",
        "lab_time": "2117-02-13 18:10:00"
    },
    {
        "lab_name": "pO2, Blood",
        "lab_value": "176.0 mm Hg",
        "lab_time": "2117-02-13 18:10:00"
    },
    {
        "lab_name": "Creatinine, Blood",
        "lab_value": "5.5 mg/dL",
        "lab_time": "2117-02-14 02:50:00"
    },
    {
        "lab_name": "Troponin T, Blood",
        "lab_value": "0.3 ng/mL",
        "lab_time": "2117-02-14 02:50:00"
    },
    {
        "lab_name": "Urea Nitrogen, Blood",
        "lab_value": "31.0 mg/dL",
        "lab_time": "2117-02-14 02:50:00"
    },
    {
        "lab_name": "Hematocrit, Blood",
        "lab_value": "36.5 %",
        "lab_time": "2117-02-14 02:50:00"
    },
    {
        "lab_name": "Hemoglobin, Blood",
        "lab_value": "11.6 g/dL",
        "lab_time": "2117-02-14 02:50:00"
    },
    {
        "lab_name": "MCH, Blood",
        "lab_value": "33.8 pg",
        "lab_time": "2117-02-14 02:50:00"
    },
    {
        "lab_name": "MCV, Blood",
        "lab_value": "107.0 fL",
        "lab_time": "2117-02-14 02:50:00"
    },
    {
        "lab_name": "Platelet Count, Blood",
        "lab_value": "144.0 K/uL",
        "lab_time": "2117-02-14 02:50:00"
    },
    {
        "lab_name": "RDW, Blood",
        "lab_value": "17.7 %",
        "lab_time": "2117-02-14 02:50:00"
    },
    {
        "lab_name": "Red Blood Cells, Blood",
        "lab_value": "3.43 m/uL",
        "lab_time": "2117-02-14 02:50:00"
    },
    {
        "lab_name": "Creatine Kinase (CK), Blood",
        "lab_value": "234.0 IU/L",
        "lab_time": "2117-02-14 07:40:00"
    },
    {
        "lab_name": "Troponin T, Blood",
        "lab_value": "0.23 ng/mL",
        "lab_time": "2117-02-14 07:40:00"
    },
    {
        "lab_name": "Creatinine, Blood",
        "lab_value": "6.5 mg/dL",
        "lab_time": "2117-02-15 05:30:00"
    },
    {
        "lab_name": "Urea Nitrogen, Blood",
        "lab_value": "45.0 mg/dL",
        "lab_time": "2117-02-15 05:30:00"
    },
    {
        "lab_name": "Hematocrit, Blood",
        "lab_value": "35.3 %",
        "lab_time": "2117-02-15 05:30:00"
    },
    {
        "lab_name": "Hemoglobin, Blood",
        "lab_value": "11.5 g/dL",
        "lab_time": "2117-02-15 05:30:00"
    },
    {
        "lab_name": "MCH, Blood",
        "lab_value": "34.2 pg",
        "lab_time": "2117-02-15 05:30:00"
    },
    {
        "lab_name": "MCV, Blood",
        "lab_value": "105.0 fL",
        "lab_time": "2117-02-15 05:30:00"
    },
    {
        "lab_name": "Platelet Count, Blood",
        "lab_value": "136.0 K/uL",
        "lab_time": "2117-02-15 05:30:00"
    },
    {
        "lab_name": "RDW, Blood",
        "lab_value": "17.8 %",
        "lab_time": "2117-02-15 05:30:00"
    },
    {
        "lab_name": "Red Blood Cells, Blood",
        "lab_value": "3.35 m/uL",
        "lab_time": "2117-02-15 05:30:00"
    },
    {
        "lab_name": "Lymphocytes, Pleural",
        "lab_value": "87.0 %",
        "lab_time": "2117-02-15 15:45:00"
    },
    {
        "lab_name": "Mesothelial Cells, Pleural",
        "lab_value": "2.0 %",
        "lab_time": "2117-02-15 15:45:00"
    },
    {
        "lab_name": "Monos, Pleural",
        "lab_value": "10.0 %",
        "lab_time": "2117-02-15 15:45:00"
    },
    {
        "lab_name": "Polys, Pleural",
        "lab_value": "1.0 %",
        "lab_time": "2117-02-15 15:45:00"
    },
    {
        "lab_name": "RBC, Pleural, Pleural",
        "lab_value": "140.0 #/uL",
        "lab_time": "2117-02-15 15:45:00"
    },
    {
        "lab_name": "WBC, Pleural, Pleural",
        "lab_value": "200.0 #/uL",
        "lab_time": "2117-02-15 15:45:00"
    },
    {
        "lab_name": "Creatinine, Blood",
        "lab_value": "5.2 mg/dL",
        "lab_time": "2117-02-16 06:00:00"
    },
    {
        "lab_name": "Urea Nitrogen, Blood",
        "lab_value": "28.0 mg/dL",
        "lab_time": "2117-02-16 06:00:00"
    },
    {
        "lab_name": "Hematocrit, Blood",
        "lab_value": "33.2 %",
        "lab_time": "2117-02-16 06:00:00"
    },
    {
        "lab_name": "Hemoglobin, Blood",
        "lab_value": "10.6 g/dL",
        "lab_time": "2117-02-16 06:00:00"
    },
    {
        "lab_name": "MCH, Blood",
        "lab_value": "33.3 pg",
        "lab_time": "2117-02-16 06:00:00"
    },
    {
        "lab_name": "MCV, Blood",
        "lab_value": "105.0 fL",
        "lab_time": "2117-02-16 06:00:00"
    },
    {
        "lab_name": "Platelet Count, Blood",
        "lab_value": "121.0 K/uL",
        "lab_time": "2117-02-16 06:00:00"
    },
    {
        "lab_name": "RDW, Blood",
        "lab_value": "17.9 %",
        "lab_time": "2117-02-16 06:00:00"
    },
    {
        "lab_name": "Red Blood Cells, Blood",
        "lab_value": "3.17 m/uL",
        "lab_time": "2117-02-16 06:00:00"
    },
    {
        "lab_name": "Creatinine, Blood",
        "lab_value": "6.6 mg/dL",
        "lab_time": "2117-02-17 07:10:00"
    },
    {
        "lab_name": "Glucose, Blood",
        "lab_value": "123.0 mg/dL",
        "lab_time": "2117-02-17 07:10:00"
    },
    {
        "lab_name": "Urea Nitrogen, Blood",
        "lab_value": "39.0 mg/dL",
        "lab_time": "2117-02-17 07:10:00"
    },
    {
        "lab_name": "Hematocrit, Blood",
        "lab_value": "32.0 %",
        "lab_time": "2117-02-17 07:10:00"
    },
    {
        "lab_name": "Hemoglobin, Blood",
        "lab_value": "10.4 g/dL",
        "lab_time": "2117-02-17 07:10:00"
    },
    {
        "lab_name": "MCH, Blood",
        "lab_value": "34.3 pg",
        "lab_time": "2117-02-17 07:10:00"
    },
    {
        "lab_name": "MCV, Blood",
        "lab_value": "105.0 fL",
        "lab_time": "2117-02-17 07:10:00"
    },
    {
        "lab_name": "Platelet Count, Blood",
        "lab_value": "113.0 K/uL",
        "lab_time": "2117-02-17 07:10:00"
    },
    {
        "lab_name": "RDW, Blood",
        "lab_value": "19.4 %",
        "lab_time": "2117-02-17 07:10:00"
    },
    {
        "lab_name": "Red Blood Cells, Blood",
        "lab_value": "3.04 m/uL",
        "lab_time": "2117-02-17 07:10:00"
    },
    {
        "lab_name": "Creatinine, Blood",
        "lab_value": "4.3 mg/dL",
        "lab_time": "2117-03-13 05:00:00"
    },
    {
        "lab_name": "Glucose, Blood",
        "lab_value": "114.0 mg/dL",
        "lab_time": "2117-03-13 05:00:00"
    },
    {
        "lab_name": "Urea Nitrogen, Blood",
        "lab_value": "25.0 mg/dL",
        "lab_time": "2117-03-13 05:00:00"
    },
    {
        "lab_name": "Hematocrit, Blood",
        "lab_value": "34.2 %",
        "lab_time": "2117-03-13 05:00:00"
    },
    {
        "lab_name": "Hemoglobin, Blood",
        "lab_value": "11.1 g/dL",
        "lab_time": "2117-03-13 05:00:00"
    },
    {
        "lab_name": "Lymphocytes, Blood",
        "lab_value": "9.4 %",
        "lab_time": "2117-03-13 05:00:00"
    },
    {
        "lab_name": "MCH, Blood",
        "lab_value": "34.6 pg",
        "lab_time": "2117-03-13 05:00:00"
    },
    {
        "lab_name": "MCV, Blood",
        "lab_value": "106.0 fL",
        "lab_time": "2117-03-13 05:00:00"
    },
    {
        "lab_name": "Neutrophils, Blood",
        "lab_value": "85.4 %",
        "lab_time": "2117-03-13 05:00:00"
    },
    {
        "lab_name": "Platelet Count, Blood",
        "lab_value": "134.0 K/uL",
        "lab_time": "2117-03-13 05:00:00"
    },
    {
        "lab_name": "RDW, Blood",
        "lab_value": "19.6 %",
        "lab_time": "2117-03-13 05:00:00"
    },
    {
        "lab_name": "Red Blood Cells, Blood",
        "lab_value": "3.22 m/uL",
        "lab_time": "2117-03-13 05:00:00"
    },
    {
        "lab_name": "Asparate Aminotransferase (AST), Blood",
        "lab_value": "41.0 IU/L",
        "lab_time": "2117-03-16 17:16:00"
    },
    {
        "lab_name": "Bilirubin, Total, Blood",
        "lab_value": "1.9 mg/dL",
        "lab_time": "2117-03-16 17:16:00"
    },
    {
        "lab_name": "Creatinine, Blood",
        "lab_value": "5.6 mg/dL",
        "lab_time": "2117-03-16 17:16:00"
    },
    {
        "lab_name": "Sodium, Blood",
        "lab_value": "146.0 mEq/L",
        "lab_time": "2117-03-16 17:16:00"
    },
    {
        "lab_name": "Urea Nitrogen, Blood",
        "lab_value": "36.0 mg/dL",
        "lab_time": "2117-03-16 17:16:00"
    },
    {
        "lab_name": "Hematocrit, Blood",
        "lab_value": "32.6 %",
        "lab_time": "2117-03-16 17:16:00"
    },
    {
        "lab_name": "Hemoglobin, Blood",
        "lab_value": "10.8 g/dL",
        "lab_time": "2117-03-16 17:16:00"
    },
    {
        "lab_name": "INR(PT), Blood",
        "lab_value": "1.3",
        "lab_time": "2117-03-16 17:16:00"
    },
    {
        "lab_name": "Lymphocytes, Blood",
        "lab_value": "13.0 %",
        "lab_time": "2117-03-16 17:16:00"
    },
    {
        "lab_name": "MCH, Blood",
        "lab_value": "34.5 pg",
        "lab_time": "2117-03-16 17:16:00"
    },
    {
        "lab_name": "MCV, Blood",
        "lab_value": "104.0 fL",
        "lab_time": "2117-03-16 17:16:00"
    },
    {
        "lab_name": "Neutrophils, Blood",
        "lab_value": "80.6 %",
        "lab_time": "2117-03-16 17:16:00"
    },
    {
        "lab_name": "Platelet Count, Blood",
        "lab_value": "123.0 K/uL",
        "lab_time": "2117-03-16 17:16:00"
    },
    {
        "lab_name": "PT, Blood",
        "lab_value": "14.7 sec",
        "lab_time": "2117-03-16 17:16:00"
    },
    {
        "lab_name": "RDW, Blood",
        "lab_value": "20.1 %",
        "lab_time": "2117-03-16 17:16:00"
    },
    {
        "lab_name": "Red Blood Cells, Blood",
        "lab_value": "3.12 m/uL",
        "lab_time": "2117-03-16 17:16:00"
    },
    {
        "lab_name": "Creatinine, Blood",
        "lab_value": "6.0 mg/dL",
        "lab_time": "2117-03-17 04:00:00"
    },
    {
        "lab_name": "Digoxin, Blood",
        "lab_value": "0.5 ng/mL",
        "lab_time": "2117-03-17 04:00:00"
    },
    {
        "lab_name": "Ferritin, Blood",
        "lab_value": "1384.0 ng/mL",
        "lab_time": "2117-03-17 04:00:00"
    },
    {
        "lab_name": "Iron Binding Capacity, Total, Blood",
        "lab_value": "181.0 ug/dL",
        "lab_time": "2117-03-17 04:00:00"
    },
    {
        "lab_name": "Transferrin, Blood",
        "lab_value": "139.0 mg/dL",
        "lab_time": "2117-03-17 04:00:00"
    },
    {
        "lab_name": "Urea Nitrogen, Blood",
        "lab_value": "40.0 mg/dL",
        "lab_time": "2117-03-17 04:00:00"
    },
    {
        "lab_name": "Vitamin B12, Blood",
        "lab_value": "1608.0 pg/mL",
        "lab_time": "2117-03-17 04:00:00"
    },
    {
        "lab_name": "Hematocrit, Blood",
        "lab_value": "29.0 %",
        "lab_time": "2117-03-17 04:00:00"
    },
    {
        "lab_name": "Hemoglobin, Blood",
        "lab_value": "9.6 g/dL",
        "lab_time": "2117-03-17 04:00:00"
    },
    {
        "lab_name": "MCH, Blood",
        "lab_value": "35.3 pg",
        "lab_time": "2117-03-17 04:00:00"
    },
    {
        "lab_name": "MCV, Blood",
        "lab_value": "107.0 fL",
        "lab_time": "2117-03-17 04:00:00"
    },
    {
        "lab_name": "Platelet Count, Blood",
        "lab_value": "101.0 K/uL",
        "lab_time": "2117-03-17 04:00:00"
    },
    {
        "lab_name": "RDW, Blood",
        "lab_value": "21.3 %",
        "lab_time": "2117-03-17 04:00:00"
    },
    {
        "lab_name": "Red Blood Cells, Blood",
        "lab_value": "2.72 m/uL",
        "lab_time": "2117-03-17 04:00:00"
    },
    {
        "lab_name": "Asparate Aminotransferase (AST), Blood",
        "lab_value": "55.0 IU/L",
        "lab_time": "2118-05-20 08:00:00"
    },
    {
        "lab_name": "Bilirubin, Total, Blood",
        "lab_value": "2.0 mg/dL",
        "lab_time": "2118-05-20 08:00:00"
    },
    {
        "lab_name": "Creatinine, Blood",
        "lab_value": "4.5 mg/dL",
        "lab_time": "2118-05-20 08:00:00"
    },
    {
        "lab_name": "Potassium, Blood",
        "lab_value": "6.2 mEq/L",
        "lab_time": "2118-05-20 08:00:00"
    },
    {
        "lab_name": "Troponin T, Blood",
        "lab_value": "0.35 ng/mL",
        "lab_time": "2118-05-20 08:00:00"
    },
    {
        "lab_name": "Urea Nitrogen, Blood",
        "lab_value": "32.0 mg/dL",
        "lab_time": "2118-05-20 08:00:00"
    },
    {
        "lab_name": "Hematocrit, Blood",
        "lab_value": "39.0 %",
        "lab_time": "2118-05-20 08:00:00"
    },
    {
        "lab_name": "Hemoglobin, Blood",
        "lab_value": "11.9 g/dL",
        "lab_time": "2118-05-20 08:00:00"
    },
    {
        "lab_name": "INR(PT), Blood",
        "lab_value": "1.5",
        "lab_time": "2118-05-20 08:00:00"
    },
    {
        "lab_name": "Lymphocytes, Blood",
        "lab_value": "3.0 %",
        "lab_time": "2118-05-20 08:00:00"
    },
    {
        "lab_name": "MCH, Blood",
        "lab_value": "33.6 pg",
        "lab_time": "2118-05-20 08:00:00"
    },
    {
        "lab_name": "MCHC, Blood",
        "lab_value": "30.4 %",
        "lab_time": "2118-05-20 08:00:00"
    },
    {
        "lab_name": "MCV, Blood",
        "lab_value": "110.0 fL",
        "lab_time": "2118-05-20 08:00:00"
    },
    {
        "lab_name": "Neutrophils, Blood",
        "lab_value": "94.0 %",
        "lab_time": "2118-05-20 08:00:00"
    },
    {
        "lab_name": "PT, Blood",
        "lab_value": "16.6 sec",
        "lab_time": "2118-05-20 08:00:00"
    },
    {
        "lab_name": "RDW, Blood",
        "lab_value": "17.6 %",
        "lab_time": "2118-05-20 08:00:00"
    },
    {
        "lab_name": "Red Blood Cells, Blood",
        "lab_value": "3.54 m/uL",
        "lab_time": "2118-05-20 08:00:00"
    },
    {
        "lab_name": "White Blood Cells, Blood",
        "lab_value": "17.7 K/uL",
        "lab_time": "2118-05-20 08:00:00"
    },
    {
        "lab_name": "Hemoglobin, Blood",
        "lab_value": "12.9 g/dL",
        "lab_time": "2118-05-20 08:05:00"
    },
    {
        "lab_name": "Lactate, Blood",
        "lab_value": "3.8 mmol/L",
        "lab_time": "2118-05-20 08:05:00"
    },
    {
        "lab_name": "Potassium, Whole Blood, Blood",
        "lab_value": "5.6 mEq/L",
        "lab_time": "2118-05-20 08:05:00"
    },
    {
        "lab_name": "Albumin, Blood",
        "lab_value": "3.0 g/dL",
        "lab_time": "2118-05-21 01:01:00"
    },
    {
        "lab_name": "Alkaline Phosphatase, Blood",
        "lab_value": "149.0 IU/L",
        "lab_time": "2118-05-21 01:01:00"
    },
    {
        "lab_name": "Creatinine, Blood",
        "lab_value": "2.5 mg/dL",
        "lab_time": "2118-05-21 01:01:00"
    },
    {
        "lab_name": "Hematocrit, Blood",
        "lab_value": "30.9 %",
        "lab_time": "2118-05-21 01:01:00"
    },
    {
        "lab_name": "Hemoglobin, Blood",
        "lab_value": "9.6 g/dL",
        "lab_time": "2118-05-21 01:01:00"
    },
    {
        "lab_name": "INR(PT), Blood",
        "lab_value": "1.6",
        "lab_time": "2118-05-21 01:01:00"
    },
    {
        "lab_name": "MCH, Blood",
        "lab_value": "33.4 pg",
        "lab_time": "2118-05-21 01:01:00"
    },
    {
        "lab_name": "MCV, Blood",
        "lab_value": "108.0 fL",
        "lab_time": "2118-05-21 01:01:00"
    },
    {
        "lab_name": "PT, Blood",
        "lab_value": "18.2 sec",
        "lab_time": "2118-05-21 01:01:00"
    },
    {
        "lab_name": "RDW, Blood",
        "lab_value": "17.5 %",
        "lab_time": "2118-05-21 01:01:00"
    },
    {
        "lab_name": "Red Blood Cells, Blood",
        "lab_value": "2.87 m/uL",
        "lab_time": "2118-05-21 01:01:00"
    },
    {
        "lab_name": "White Blood Cells, Blood",
        "lab_value": "12.1 K/uL",
        "lab_time": "2118-05-21 01:01:00"
    },
    {
        "lab_name": "Alkaline Phosphatase, Blood",
        "lab_value": "160.0 IU/L",
        "lab_time": "2118-05-22 02:33:00"
    },
    {
        "lab_name": "Creatinine, Blood",
        "lab_value": "3.9 mg/dL",
        "lab_time": "2118-05-22 02:33:00"
    },
    {
        "lab_name": "Urea Nitrogen, Blood",
        "lab_value": "26.0 mg/dL",
        "lab_time": "2118-05-22 02:33:00"
    },
    {
        "lab_name": "Vancomycin, Blood",
        "lab_value": "8.1 ug/mL",
        "lab_time": "2118-05-22 02:33:00"
    },
    {
        "lab_name": "Hematocrit, Blood",
        "lab_value": "31.3 %",
        "lab_time": "2118-05-22 02:33:00"
    },
    {
        "lab_name": "Hemoglobin, Blood",
        "lab_value": "9.7 g/dL",
        "lab_time": "2118-05-22 02:33:00"
    },
    {
        "lab_name": "INR(PT), Blood",
        "lab_value": "1.4",
        "lab_time": "2118-05-22 02:33:00"
    },
    {
        "lab_name": "MCH, Blood",
        "lab_value": "33.7 pg",
        "lab_time": "2118-05-22 02:33:00"
    },
    {
        "lab_name": "MCHC, Blood",
        "lab_value": "30.8 %",
        "lab_time": "2118-05-22 02:33:00"
    },
    {
        "lab_name": "MCV, Blood",
        "lab_value": "109.0 fL",
        "lab_time": "2118-05-22 02:33:00"
    },
    {
        "lab_name": "PT, Blood",
        "lab_value": "16.1 sec",
        "lab_time": "2118-05-22 02:33:00"
    },
    {
        "lab_name": "RDW, Blood",
        "lab_value": "17.3 %",
        "lab_time": "2118-05-22 02:33:00"
    },
    {
        "lab_name": "Red Blood Cells, Blood",
        "lab_value": "2.87 m/uL",
        "lab_time": "2118-05-22 02:33:00"
    },
    {
        "lab_name": "Creatinine, Blood",
        "lab_value": "5.2 mg/dL",
        "lab_time": "2118-05-23 06:30:00"
    },
    {
        "lab_name": "Phosphate, Blood",
        "lab_value": "5.6 mg/dL",
        "lab_time": "2118-05-23 06:30:00"
    },
    {
        "lab_name": "Urea Nitrogen, Blood",
        "lab_value": "37.0 mg/dL",
        "lab_time": "2118-05-23 06:30:00"
    },
    {
        "lab_name": "Hematocrit, Blood",
        "lab_value": "30.8 %",
        "lab_time": "2118-05-23 06:30:00"
    },
    {
        "lab_name": "Hemoglobin, Blood",
        "lab_value": "9.7 g/dL",
        "lab_time": "2118-05-23 06:30:00"
    },
    {
        "lab_name": "INR(PT), Blood",
        "lab_value": "1.2",
        "lab_time": "2118-05-23 06:30:00"
    },
    {
        "lab_name": "MCH, Blood",
        "lab_value": "33.8 pg",
        "lab_time": "2118-05-23 06:30:00"
    },
    {
        "lab_name": "MCV, Blood",
        "lab_value": "108.0 fL",
        "lab_time": "2118-05-23 06:30:00"
    },
    {
        "lab_name": "PT, Blood",
        "lab_value": "14.4 sec",
        "lab_time": "2118-05-23 06:30:00"
    },
    {
        "lab_name": "RDW, Blood",
        "lab_value": "16.3 %",
        "lab_time": "2118-05-23 06:30:00"
    },
    {
        "lab_name": "Red Blood Cells, Blood",
        "lab_value": "2.86 m/uL",
        "lab_time": "2118-05-23 06:30:00"
    },
    {
        "lab_name": "Bicarbonate, Blood",
        "lab_value": "34.0 mEq/L",
        "lab_time": "2118-05-24 06:45:00"
    },
    {
        "lab_name": "Creatinine, Blood",
        "lab_value": "3.4 mg/dL",
        "lab_time": "2118-05-24 06:45:00"
    },
    {
        "lab_name": "Urea Nitrogen, Blood",
        "lab_value": "21.0 mg/dL",
        "lab_time": "2118-05-24 06:45:00"
    },
    {
        "lab_name": "Hematocrit, Blood",
        "lab_value": "34.3 %",
        "lab_time": "2118-05-24 06:45:00"
    },
    {
        "lab_name": "Hemoglobin, Blood",
        "lab_value": "10.4 g/dL",
        "lab_time": "2118-05-24 06:45:00"
    },
    {
        "lab_name": "INR(PT), Blood",
        "lab_value": "1.3",
        "lab_time": "2118-05-24 06:45:00"
    },
    {
        "lab_name": "MCH, Blood",
        "lab_value": "32.6 pg",
        "lab_time": "2118-05-24 06:45:00"
    },
    {
        "lab_name": "MCHC, Blood",
        "lab_value": "30.2 %",
        "lab_time": "2118-05-24 06:45:00"
    },
    {
        "lab_name": "MCV, Blood",
        "lab_value": "108.0 fL",
        "lab_time": "2118-05-24 06:45:00"
    },
    {
        "lab_name": "PT, Blood",
        "lab_value": "14.5 sec",
        "lab_time": "2118-05-24 06:45:00"
    },
    {
        "lab_name": "RDW, Blood",
        "lab_value": "16.1 %",
        "lab_time": "2118-05-24 06:45:00"
    },
    {
        "lab_name": "Red Blood Cells, Blood",
        "lab_value": "3.17 m/uL",
        "lab_time": "2118-05-24 06:45:00"
    },
    {
        "lab_name": "Creatinine, Blood",
        "lab_value": "4.4 mg/dL",
        "lab_time": "2118-05-25 05:50:00"
    },
    {
        "lab_name": "Phosphate, Blood",
        "lab_value": "4.7 mg/dL",
        "lab_time": "2118-05-25 05:50:00"
    },
    {
        "lab_name": "Urea Nitrogen, Blood",
        "lab_value": "32.0 mg/dL",
        "lab_time": "2118-05-25 05:50:00"
    },
    {
        "lab_name": "Hematocrit, Blood",
        "lab_value": "31.4 %",
        "lab_time": "2118-05-25 05:50:00"
    },
    {
        "lab_name": "Hemoglobin, Blood",
        "lab_value": "10.0 g/dL",
        "lab_time": "2118-05-25 05:50:00"
    },
    {
        "lab_name": "MCH, Blood",
        "lab_value": "34.2 pg",
        "lab_time": "2118-05-25 05:50:00"
    },
    {
        "lab_name": "MCV, Blood",
        "lab_value": "107.0 fL",
        "lab_time": "2118-05-25 05:50:00"
    },
    {
        "lab_name": "RDW, Blood",
        "lab_value": "17.0 %",
        "lab_time": "2118-05-25 05:50:00"
    },
    {
        "lab_name": "Red Blood Cells, Blood",
        "lab_value": "2.94 m/uL",
        "lab_time": "2118-05-25 05:50:00"
    },
    {
        "lab_name": "Creatinine, Blood",
        "lab_value": "3.6 mg/dL",
        "lab_time": "2118-05-26 06:55:00"
    },
    {
        "lab_name": "Hematocrit, Blood",
        "lab_value": "32.6 %",
        "lab_time": "2118-05-26 06:55:00"
    },
    {
        "lab_name": "Hemoglobin, Blood",
        "lab_value": "9.9 g/dL",
        "lab_time": "2118-05-26 06:55:00"
    },
    {
        "lab_name": "INR(PT), Blood",
        "lab_value": "1.4",
        "lab_time": "2118-05-26 06:55:00"
    },
    {
        "lab_name": "MCH, Blood",
        "lab_value": "32.9 pg",
        "lab_time": "2118-05-26 06:55:00"
    },
    {
        "lab_name": "MCHC, Blood",
        "lab_value": "30.5 %",
        "lab_time": "2118-05-26 06:55:00"
    },
    {
        "lab_name": "MCV, Blood",
        "lab_value": "108.0 fL",
        "lab_time": "2118-05-26 06:55:00"
    },
    {
        "lab_name": "PT, Blood",
        "lab_value": "16.1 sec",
        "lab_time": "2118-05-26 06:55:00"
    },
    {
        "lab_name": "RDW, Blood",
        "lab_value": "16.3 %",
        "lab_time": "2118-05-26 06:55:00"
    },
    {
        "lab_name": "Red Blood Cells, Blood",
        "lab_value": "3.01 m/uL",
        "lab_time": "2118-05-26 06:55:00"
    },
    {
        "lab_name": "Lymphocytes, Ascites",
        "lab_value": "14.0 %",
        "lab_time": "2117-03-17 07:52:00"
    },
    {
        "lab_name": "Macrophage, Ascites",
        "lab_value": "79.0 %",
        "lab_time": "2117-03-17 07:52:00"
    },
    {
        "lab_name": "Mesothelial Cell, Ascites",
        "lab_value": "2.0 %",
        "lab_time": "2117-03-17 07:52:00"
    },
    {
        "lab_name": "Polys, Ascites",
        "lab_value": "5.0 %",
        "lab_time": "2117-03-17 07:52:00"
    },
    {
        "lab_name": "RBC, Ascites, Ascites",
        "lab_value": "92.0 #/uL",
        "lab_time": "2117-03-17 07:52:00"
    },
    {
        "lab_name": "WBC, Ascites, Ascites",
        "lab_value": "50.0 #/uL",
        "lab_time": "2117-03-17 07:52:00"
    },
    {
        "lab_name": "Parathyroid Hormone, Blood",
        "lab_value": "133.0 pg/mL",
        "lab_time": "2117-03-17 10:56:00"
    },
    {
        "lab_name": "Bilirubin, Total, Blood",
        "lab_value": "1.7 mg/dL",
        "lab_time": "2117-03-18 04:15:00"
    },
    {
        "lab_name": "Creatinine, Blood",
        "lab_value": "3.8 mg/dL",
        "lab_time": "2117-03-18 04:15:00"
    },
    {
        "lab_name": "Lactate Dehydrogenase (LD), Blood",
        "lab_value": "258.0 IU/L",
        "lab_time": "2117-03-18 04:15:00"
    },
    {
        "lab_name": "Hematocrit, Blood",
        "lab_value": "30.1 %",
        "lab_time": "2117-03-18 04:15:00"
    },
    {
        "lab_name": "Hemoglobin, Blood",
        "lab_value": "9.6 g/dL",
        "lab_time": "2117-03-18 04:15:00"
    },
    {
        "lab_name": "INR(PT), Blood",
        "lab_value": "1.3",
        "lab_time": "2117-03-18 04:15:00"
    },
    {
        "lab_name": "MCH, Blood",
        "lab_value": "34.2 pg",
        "lab_time": "2117-03-18 04:15:00"
    },
    {
        "lab_name": "MCV, Blood",
        "lab_value": "108.0 fL",
        "lab_time": "2117-03-18 04:15:00"
    },
    {
        "lab_name": "Platelet Count, Blood",
        "lab_value": "87.0 K/uL",
        "lab_time": "2117-03-18 04:15:00"
    },
    {
        "lab_name": "PT, Blood",
        "lab_value": "15.1 sec",
        "lab_time": "2117-03-18 04:15:00"
    },
    {
        "lab_name": "RDW, Blood",
        "lab_value": "20.8 %",
        "lab_time": "2117-03-18 04:15:00"
    },
    {
        "lab_name": "Red Blood Cells, Blood",
        "lab_value": "2.8 m/uL",
        "lab_time": "2117-03-18 04:15:00"
    },
    {
        "lab_name": "Creatinine, Blood",
        "lab_value": "5.3 mg/dL",
        "lab_time": "2117-03-19 03:55:00"
    },
    {
        "lab_name": "Lactate Dehydrogenase (LD), Blood",
        "lab_value": "276.0 IU/L",
        "lab_time": "2117-03-19 03:55:00"
    },
    {
        "lab_name": "Urea Nitrogen, Blood",
        "lab_value": "27.0 mg/dL",
        "lab_time": "2117-03-19 03:55:00"
    },
    {
        "lab_name": "Hematocrit, Blood",
        "lab_value": "33.3 %",
        "lab_time": "2117-03-19 03:55:00"
    },
    {
        "lab_name": "Hemoglobin, Blood",
        "lab_value": "10.9 g/dL",
        "lab_time": "2117-03-19 03:55:00"
    },
    {
        "lab_name": "INR(PT), Blood",
        "lab_value": "1.2",
        "lab_time": "2117-03-19 03:55:00"
    },
    {
        "lab_name": "MCH, Blood",
        "lab_value": "35.8 pg",
        "lab_time": "2117-03-19 03:55:00"
    },
    {
        "lab_name": "MCV, Blood",
        "lab_value": "109.0 fL",
        "lab_time": "2117-03-19 03:55:00"
    },
    {
        "lab_name": "Platelet Count, Blood",
        "lab_value": "108.0 K/uL",
        "lab_time": "2117-03-19 03:55:00"
    },
    {
        "lab_name": "PT, Blood",
        "lab_value": "13.8 sec",
        "lab_time": "2117-03-19 03:55:00"
    },
    {
        "lab_name": "RDW, Blood",
        "lab_value": "22.1 %",
        "lab_time": "2117-03-19 03:55:00"
    },
    {
        "lab_name": "Red Blood Cells, Blood",
        "lab_value": "3.06 m/uL",
        "lab_time": "2117-03-19 03:55:00"
    },
    {
        "lab_name": "Creatinine, Blood",
        "lab_value": "4.0 mg/dL",
        "lab_time": "2117-03-20 08:15:00"
    },
    {
        "lab_name": "Glucose, Blood",
        "lab_value": "119.0 mg/dL",
        "lab_time": "2117-03-20 08:15:00"
    },
    {
        "lab_name": "Lactate Dehydrogenase (LD), Blood",
        "lab_value": "275.0 IU/L",
        "lab_time": "2117-03-20 08:15:00"
    },
    {
        "lab_name": "Hematocrit, Blood",
        "lab_value": "34.7 %",
        "lab_time": "2117-03-20 08:15:00"
    },
    {
        "lab_name": "Hemoglobin, Blood",
        "lab_value": "11.2 g/dL",
        "lab_time": "2117-03-20 08:15:00"
    },
    {
        "lab_name": "INR(PT), Blood",
        "lab_value": "1.2",
        "lab_time": "2117-03-20 08:15:00"
    },
    {
        "lab_name": "MCH, Blood",
        "lab_value": "34.3 pg",
        "lab_time": "2117-03-20 08:15:00"
    },
    {
        "lab_name": "MCV, Blood",
        "lab_value": "107.0 fL",
        "lab_time": "2117-03-20 08:15:00"
    },
    {
        "lab_name": "Platelet Count, Blood",
        "lab_value": "100.0 K/uL",
        "lab_time": "2117-03-20 08:15:00"
    },
    {
        "lab_name": "PT, Blood",
        "lab_value": "14.2 sec",
        "lab_time": "2117-03-20 08:15:00"
    },
    {
        "lab_name": "RDW, Blood",
        "lab_value": "21.1 %",
        "lab_time": "2117-03-20 08:15:00"
    },
    {
        "lab_name": "Red Blood Cells, Blood",
        "lab_value": "3.25 m/uL",
        "lab_time": "2117-03-20 08:15:00"
    },
    {
        "lab_name": "Creatinine, Blood",
        "lab_value": "5.4 mg/dL",
        "lab_time": "2117-03-21 05:20:00"
    },
    {
        "lab_name": "Lactate Dehydrogenase (LD), Blood",
        "lab_value": "287.0 IU/L",
        "lab_time": "2117-03-21 05:20:00"
    },
    {
        "lab_name": "Sodium, Blood",
        "lab_value": "146.0 mEq/L",
        "lab_time": "2117-03-21 05:20:00"
    },
    {
        "lab_name": "Thyroid Stimulating Hormone, Blood",
        "lab_value": "8.3 uIU/mL",
        "lab_time": "2117-03-21 05:20:00"
    },
    {
        "lab_name": "Urea Nitrogen, Blood",
        "lab_value": "31.0 mg/dL",
        "lab_time": "2117-03-21 05:20:00"
    },
    {
        "lab_name": "Hematocrit, Blood",
        "lab_value": "33.9 %",
        "lab_time": "2117-03-21 05:20:00"
    },
    {
        "lab_name": "Hemoglobin, Blood",
        "lab_value": "11.1 g/dL",
        "lab_time": "2117-03-21 05:20:00"
    },
    {
        "lab_name": "INR(PT), Blood",
        "lab_value": "1.3",
        "lab_time": "2117-03-21 05:20:00"
    },
    {
        "lab_name": "MCH, Blood",
        "lab_value": "35.9 pg",
        "lab_time": "2117-03-21 05:20:00"
    },
    {
        "lab_name": "MCV, Blood",
        "lab_value": "110.0 fL",
        "lab_time": "2117-03-21 05:20:00"
    },
    {
        "lab_name": "Platelet Count, Blood",
        "lab_value": "110.0 K/uL",
        "lab_time": "2117-03-21 05:20:00"
    },
    {
        "lab_name": "PT, Blood",
        "lab_value": "14.4 sec",
        "lab_time": "2117-03-21 05:20:00"
    },
    {
        "lab_name": "RDW, Blood",
        "lab_value": "22.1 %",
        "lab_time": "2117-03-21 05:20:00"
    },
    {
        "lab_name": "Red Blood Cells, Blood",
        "lab_value": "3.09 m/uL",
        "lab_time": "2117-03-21 05:20:00"
    },
    {
        "lab_name": "Creatinine, Blood",
        "lab_value": "6.5 mg/dL",
        "lab_time": "2117-03-22 04:35:00"
    },
    {
        "lab_name": "Lactate Dehydrogenase (LD), Blood",
        "lab_value": "258.0 IU/L",
        "lab_time": "2117-03-22 04:35:00"
    },
    {
        "lab_name": "Thyroxine (T4), Blood",
        "lab_value": "4.4 ug/dL",
        "lab_time": "2117-03-22 04:35:00"
    },
    {
        "lab_name": "Urea Nitrogen, Blood",
        "lab_value": "41.0 mg/dL",
        "lab_time": "2117-03-22 04:35:00"
    },
    {
        "lab_name": "Hematocrit, Blood",
        "lab_value": "31.5 %",
        "lab_time": "2117-03-22 04:35:00"
    },
    {
        "lab_name": "Hemoglobin, Blood",
        "lab_value": "10.1 g/dL",
        "lab_time": "2117-03-22 04:35:00"
    },
    {
        "lab_name": "INR(PT), Blood",
        "lab_value": "1.3",
        "lab_time": "2117-03-22 04:35:00"
    },
    {
        "lab_name": "MCH, Blood",
        "lab_value": "34.9 pg",
        "lab_time": "2117-03-22 04:35:00"
    },
    {
        "lab_name": "MCV, Blood",
        "lab_value": "108.0 fL",
        "lab_time": "2117-03-22 04:35:00"
    },
    {
        "lab_name": "Platelet Count, Blood",
        "lab_value": "119.0 K/uL",
        "lab_time": "2117-03-22 04:35:00"
    },
    {
        "lab_name": "PT, Blood",
        "lab_value": "15.0 sec",
        "lab_time": "2117-03-22 04:35:00"
    },
    {
        "lab_name": "RDW, Blood",
        "lab_value": "21.0 %",
        "lab_time": "2117-03-22 04:35:00"
    },
    {
        "lab_name": "Red Blood Cells, Blood",
        "lab_value": "2.9 m/uL",
        "lab_time": "2117-03-22 04:35:00"
    },
    {
        "lab_name": "Creatinine, Blood",
        "lab_value": "4.3 mg/dL",
        "lab_time": "2117-03-23 04:20:00"
    },
    {
        "lab_name": "Urea Nitrogen, Blood",
        "lab_value": "23.0 mg/dL",
        "lab_time": "2117-03-23 04:20:00"
    },
    {
        "lab_name": "Hematocrit, Blood",
        "lab_value": "30.8 %",
        "lab_time": "2117-03-23 04:20:00"
    },
    {
        "lab_name": "Hemoglobin, Blood",
        "lab_value": "10.1 g/dL",
        "lab_time": "2117-03-23 04:20:00"
    },
    {
        "lab_name": "INR(PT), Blood",
        "lab_value": "1.3",
        "lab_time": "2117-03-23 04:20:00"
    },
    {
        "lab_name": "MCH, Blood",
        "lab_value": "36.0 pg",
        "lab_time": "2117-03-23 04:20:00"
    },
    {
        "lab_name": "MCV, Blood",
        "lab_value": "110.0 fL",
        "lab_time": "2117-03-23 04:20:00"
    },
    {
        "lab_name": "Platelet Count, Blood",
        "lab_value": "111.0 K/uL",
        "lab_time": "2117-03-23 04:20:00"
    },
    {
        "lab_name": "PT, Blood",
        "lab_value": "15.2 sec",
        "lab_time": "2117-03-23 04:20:00"
    },
    {
        "lab_name": "RDW, Blood",
        "lab_value": "22.1 %",
        "lab_time": "2117-03-23 04:20:00"
    },
    {
        "lab_name": "Red Blood Cells, Blood",
        "lab_value": "2.81 m/uL",
        "lab_time": "2117-03-23 04:20:00"
    },
    {
        "lab_name": "Alkaline Phosphatase, Blood",
        "lab_value": "119.0 IU/L",
        "lab_time": "2117-03-24 07:00:00"
    },
    {
        "lab_name": "Creatinine, Blood",
        "lab_value": "5.7 mg/dL",
        "lab_time": "2117-03-24 07:00:00"
    },
    {
        "lab_name": "Glucose, Blood",
        "lab_value": "154.0 mg/dL",
        "lab_time": "2117-03-24 07:00:00"
    },
    {
        "lab_name": "Urea Nitrogen, Blood",
        "lab_value": "36.0 mg/dL",
        "lab_time": "2117-03-24 07:00:00"
    },
    {
        "lab_name": "Hematocrit, Blood",
        "lab_value": "29.3 %",
        "lab_time": "2117-03-24 07:00:00"
    },
    {
        "lab_name": "Hemoglobin, Blood",
        "lab_value": "9.5 g/dL",
        "lab_time": "2117-03-24 07:00:00"
    },
    {
        "lab_name": "INR(PT), Blood",
        "lab_value": "1.3",
        "lab_time": "2117-03-24 07:00:00"
    },
    {
        "lab_name": "MCH, Blood",
        "lab_value": "34.8 pg",
        "lab_time": "2117-03-24 07:00:00"
    },
    {
        "lab_name": "MCV, Blood",
        "lab_value": "107.0 fL",
        "lab_time": "2117-03-24 07:00:00"
    },
    {
        "lab_name": "Platelet Count, Blood",
        "lab_value": "141.0 K/uL",
        "lab_time": "2117-03-24 07:00:00"
    },
    {
        "lab_name": "PT, Blood",
        "lab_value": "14.9 sec",
        "lab_time": "2117-03-24 07:00:00"
    },
    {
        "lab_name": "RDW, Blood",
        "lab_value": "20.6 %",
        "lab_time": "2117-03-24 07:00:00"
    },
    {
        "lab_name": "Red Blood Cells, Blood",
        "lab_value": "2.73 m/uL",
        "lab_time": "2117-03-24 07:00:00"
    },
    {
        "lab_name": "Alkaline Phosphatase, Blood",
        "lab_value": "207.0 IU/L",
        "lab_time": "2118-05-20 08:00:00"
    },
    {
        "lab_name": "Anion Gap, Blood",
        "lab_value": "22.0 mEq/L",
        "lab_time": "2118-05-20 08:00:00"
    }
]